LICENSE
MANIFEST.in
README.rst
setup.cfg
setup.py
dynamic_load/__init__.py
dynamic_load/dynamic_execute.py
dynamic_load/dynamic_load.py
dynamic_load/dynamic_string.py
dynamic_load/tail_recursive.py
dynamic_load.egg-info/PKG-INFO
dynamic_load.egg-info/SOURCES.txt
dynamic_load.egg-info/dependency_links.txt
dynamic_load.egg-info/top_level.txt