Metadata-Version: 1.0
Name: dynamic-load
Version: 0.0.5
Summary: Load module, function from string
Home-page: https://github.com/benjamin-jin/python-dynamic-exeuction
Author: Benjamin Jin
Author-email: jinrudals135@naver.com
License: UNKNOWN
Platform: UNKNOWN
